puzzle_party-0.1.6.dist-info/METADATA
puzzle_party-0.1.6.dist-info/WHEEL
puzzle_party/__init__.py
puzzle_party/__init__.pyi
puzzle_party/py.typed
puzzle_party/puzzle_party.abi3.so
puzzle_party-0.1.6.dist-info/RECORD
